com/softalks/debug.py
com.softalks.debug-1.0.0.dist-info/METADATA
com.softalks.debug-1.0.0.dist-info/WHEEL
com.softalks.debug-1.0.0.dist-info/top_level.txt
com.softalks.debug-1.0.0.dist-info/RECORD
