Metadata-Version: 2.1
Name: com.softalks.debug
Version: 1.0.0
Summary: Easy remote debugging for Python 3
Author-email: Santiago Ruiz <hiebra@hotmail.com>
Requires-Python: >=3.0.0
